imgemb/__init__.py
imgemb/embedder.py
imgemb/semantic_search.py
imgemb/visualization.py
imgemb/cli/__init__.py
imgemb/cli/main.py
imgemb-0.2.13.dist-info/licenses/LICENSE
imgemb-0.2.13.dist-info/METADATA
imgemb-0.2.13.dist-info/WHEEL
imgemb-0.2.13.dist-info/entry_points.txt
imgemb-0.2.13.dist-info/top_level.txt
imgemb-0.2.13.dist-info/RECORD
