Metadata-Version: 2.4
Name: imgemb
Version: 0.2.13
Summary: A lightweight Python library for generating image embeddings with semantic search
Author-email: Aryan Raj <aryanraj2713@gmail.com>
License: MIT
Project-URL: Homepage, https://github.com/aryanraj2713/image_embeddings
Project-URL: Bug Tracker, https://github.com/aryanraj2713/image_embeddings/issues
Classifier: Development Status :: 3 - Alpha
Classifier: Intended Audience :: Developers
Classifier: License :: OSI Approved :: MIT License
Classifier: Operating System :: OS Independent
Classifier: Programming Language :: Python :: 3
Classifier: Programming Language :: Python :: 3.8
Classifier: Programming Language :: Python :: 3.9
Classifier: Programming Language :: Python :: 3.10
Classifier: Programming Language :: Python :: 3.11
Classifier: Programming Language :: Python :: 3.12
Classifier: Topic :: Software Development :: Libraries :: Python Modules
Classifier: Topic :: Scientific/Engineering :: Image Processing
Requires-Python: >=3.8
License-File: LICENSE
Requires-Dist: numpy>=1.19.0
Requires-Dist: opencv-python-headless>=4.5.0
Requires-Dist: pillow>=9.0.0
Requires-Dist: scikit-learn>=0.24.0
Requires-Dist: torch>=2.0.0
Requires-Dist: torchvision>=0.15.0
Requires-Dist: open-clip-torch>=2.20.0
Requires-Dist: plotly>=6.0.0
Provides-Extra: dev
Requires-Dist: pytest>=6.0; extra == "dev"
Requires-Dist: black>=21.0; extra == "dev"
Requires-Dist: flake8>=3.9; extra == "dev"
Requires-Dist: pytest-cov>=4.1.0; extra == "dev"
Requires-Dist: pytest-html>=4.1.1; extra == "dev"
Dynamic: license-file
